tszclient_py/__init__.py
tszclient_py/client.py
tszclient_py-0.2.0.dist-info/licenses/LICENSE
tszclient_py-0.2.0.dist-info/METADATA
tszclient_py-0.2.0.dist-info/WHEEL
tszclient_py-0.2.0.dist-info/top_level.txt
tszclient_py-0.2.0.dist-info/RECORD
