Metadata-Version: 2.4
Name: tszclient-py
Version: 0.2.0
Summary: Python client for Thyris Safe Zone (TSZ)
Author: Thyris AI
License: Apache-2.0
Keywords: tsz,thyris,safe-zone,pii,guardrails,llm,gateway
Requires-Python: >=3.8
License-File: LICENSE
Requires-Dist: requests>=2.0
Dynamic: license-file
